pcsx2_memory_accessor/__init__.py
pcsx2_memory_accessor/pcsx2_pine.py
pcsx2_memory_accessor/dll/libgcc_s_seh-1.dll
pcsx2_memory_accessor/dll/libpcsx2_ipc_bulk_c.dll
pcsx2_memory_accessor/dll/libstdc++-6.dll
pcsx2_memory_accessor/dll/libwinpthread-1.dll
pcsx2_memory_accessor-1.0.dist-info/METADATA
pcsx2_memory_accessor-1.0.dist-info/WHEEL
pcsx2_memory_accessor-1.0.dist-info/top_level.txt
pcsx2_memory_accessor-1.0.dist-info/RECORD
