Metadata-Version: 2.1
Name: pcsx2-memory-accessor
Version: 1.0
Summary: A Python API for reading & writing PCSX2's emulator memory, using the Pine IPC protocol.
Home-page: https://github.com/C0mposer/PCSX2-Memory-Accessor
Author: Composer
Classifier: Programming Language :: Python :: 3
Classifier: Operating System :: Microsoft :: Windows
